docs/conf.py
portfolio_optimizer/__init__.py
portfolio_optimizer/frontier.py
portfolio_optimizer/load_data.py
portfolio_optimizer/optimizer.py
portfolio_optimizer/portfolio.py
portfolio_optimizer/style.py
portfolio_optimizer0-0.3.2.dist-info/METADATA
portfolio_optimizer0-0.3.2.dist-info/WHEEL
portfolio_optimizer0-0.3.2.dist-info/licenses/LICENSE
portfolio_optimizer0-0.3.2.dist-info/RECORD
