Metadata-Version: 2.1
Name: portfolio-optimizer0
Version: 0.3.2
Summary: A library for Portfolio management and optimization
Project-URL: Homepage, https://github.com/skt27182/portfolio_optimizer.git
Project-URL: repository, https://github.com/skt27182/portfolio_optimizer.git
Project-URL: documentation, https://skt27182.github.io/portfolio_optimizer
Author-email: Shailja Kant Tiwari <shailjakant2000@gmail.com>
License: MIT License
License-File: LICENSE
Keywords: optimizer,portfolio
Classifier: License :: OSI Approved :: MIT License
Classifier: Programming Language :: Python
Classifier: Programming Language :: Python :: 3
Requires-Python: >=3.7
Requires-Dist: numpy
Requires-Dist: pandas
Requires-Dist: plotly
Requires-Dist: scipy
Requires-Dist: tabulate
Requires-Dist: tqdm
Requires-Dist: yfinance
Provides-Extra: download
